karrio/mappers/roadie/__init__.py
karrio/mappers/roadie/mapper.py
karrio/mappers/roadie/proxy.py
karrio/mappers/roadie/settings.py
karrio/plugins/roadie/__init__.py
karrio/providers/roadie/__init__.py
karrio/providers/roadie/error.py
karrio/providers/roadie/rate.py
karrio/providers/roadie/tracking.py
karrio/providers/roadie/units.py
karrio/providers/roadie/utils.py
karrio/providers/roadie/shipment/__init__.py
karrio/providers/roadie/shipment/cancel.py
karrio/providers/roadie/shipment/create.py
karrio/schemas/roadie/__init__.py
karrio/schemas/roadie/error.py
karrio/schemas/roadie/rate_request.py
karrio/schemas/roadie/rate_response.py
karrio/schemas/roadie/shipment_request.py
karrio/schemas/roadie/shipment_response.py
karrio/schemas/roadie/tracking_response.py
karrio_roadie-2026.1.4.dist-info/METADATA
karrio_roadie-2026.1.4.dist-info/WHEEL
karrio_roadie-2026.1.4.dist-info/entry_points.txt
karrio_roadie-2026.1.4.dist-info/top_level.txt
karrio_roadie-2026.1.4.dist-info/RECORD
